jhy_test/__init__.py
jhy_test/jhy_test.py
jhy_test-0.0.9.dist-info/METADATA
jhy_test-0.0.9.dist-info/WHEEL
jhy_test-0.0.9.dist-info/top_level.txt
jhy_test-0.0.9.dist-info/RECORD
