Metadata-Version: 2.1
Name: jhy-test
Version: 0.0.9
Summary: ccpy
Home-page: UNKNOWN
Author: lucete28
Author-email: 2580jhy@naver.com
License: UNKNOWN
Keywords: ccpy
Platform: UNKNOWN
Classifier: Programming Language :: Python :: 3
Classifier: Programming Language :: Python :: 3.2
Classifier: Programming Language :: Python :: 3.3
Classifier: Programming Language :: Python :: 3.4
Classifier: Programming Language :: Python :: 3.5
Classifier: Programming Language :: Python :: 3.6
Classifier: Programming Language :: Python :: 3.7
Classifier: Programming Language :: Python :: 3.11
Requires-Python: >=3
